README
setup.py
flake8_double_quotes/__init__.py
flake8_double_quotes/checks.py
flake8_double_quotes.egg-info/PKG-INFO
flake8_double_quotes.egg-info/SOURCES.txt
flake8_double_quotes.egg-info/dependency_links.txt
flake8_double_quotes.egg-info/entry_points.txt
flake8_double_quotes.egg-info/requires.txt
flake8_double_quotes.egg-info/top_level.txt