Metadata-Version: 1.1
Name: flake8-double-quotes
Version: 0.0.1
Summary: Flake8 lint to forbide single quotes.
Home-page: http://github.com/yandex-sysmon/flake8-double-quotes/
Author: Zachary Wright Heller
Author-email: UNKNOWN
License: UNKNOWN
Platform: UNKNOWN
Classifier: Development Status :: 3 - Alpha
Classifier: Environment :: Console
Classifier: Intended Audience :: Developers
Classifier: Operating System :: OS Independent
Classifier: License :: OSI Approved :: MIT License
Classifier: Programming Language :: Python
Classifier: Programming Language :: Python :: 2
Classifier: Topic :: Software Development :: Libraries :: Python Modules
Classifier: Topic :: Software Development :: Quality Assurance
